splitmovieaiyc/__init__.py
splitmovieaiyc/aiyclove.py
splitmovieaiyc-2.1.0.dist-info/METADATA
splitmovieaiyc-2.1.0.dist-info/WHEEL
splitmovieaiyc-2.1.0.dist-info/top_level.txt
splitmovieaiyc-2.1.0.dist-info/RECORD
