Metadata-Version: 2.1
Name: splitmovieaiyc
Version: 2.1.0
Summary: My first Python library
Author: Me
License: MIT
Requires-Dist: numpy (==1.21.2)
